queue_file/__init__.py
queue_file/queue_file.py
queue_file-0.1.0.dist-info/LICENSE
queue_file-0.1.0.dist-info/METADATA
queue_file-0.1.0.dist-info/WHEEL
queue_file-0.1.0.dist-info/top_level.txt
queue_file-0.1.0.dist-info/RECORD
